Topsis/__init__.py
Topsis/packagecode.py
TOPSIS_Gurjot_401853006-0.0.1.dist-info/METADATA
TOPSIS_Gurjot_401853006-0.0.1.dist-info/WHEEL
TOPSIS_Gurjot_401853006-0.0.1.dist-info/top_level.txt
TOPSIS_Gurjot_401853006-0.0.1.dist-info/RECORD
