Metadata-Version: 2.1
Name: TOPSIS-Gurjot-401853006
Version: 0.0.1
Summary: TOPSIS Analysis.
Home-page: UNKNOWN
Author: Gurjot Singh
Author-email: gurjot.pruthi@gmail.com
License: UNKNOWN
Platform: UNKNOWN
Classifier: Programming Language :: Python :: 3
Classifier: License :: OSI Approved :: MIT License
Classifier: Operating System :: OS Independent
Requires-Python: >=3.6
Requires-Dist: pandas
